qurator/__init__.py
qurator/utils/__init__.py
qurator/utils/csv.py
qurator/utils/entities.py
qurator/utils/ned.py
qurator/utils/ner.py
qurator/utils/parallel.py
qurator/utils/pickle.py
qurator/utils/qurator_data.py
qurator/utils/tsv.py
qurator_sbb_utils-0.0.1.dist-info/METADATA
qurator_sbb_utils-0.0.1.dist-info/WHEEL
qurator_sbb_utils-0.0.1.dist-info/entry_points.txt
qurator_sbb_utils-0.0.1.dist-info/top_level.txt
qurator_sbb_utils-0.0.1.dist-info/RECORD
