Metadata-Version: 2.1
Name: qurator-sbb-utils
Version: 0.0.1
Summary: Qurator
Home-page: https://github.com/qurator-spk/sbb_utils
Author: The Qurator Team
Author-email: Kai.Labusch@sbb.spk-berlin.de
License: Apache
Keywords: Qurator
Platform: UNKNOWN
Classifier: Intended Audience :: Science/Research
Classifier: License :: OSI Approved :: Apache Software License
Classifier: Programming Language :: Python :: 3
Classifier: Topic :: Scientific/Engineering :: Artificial Intelligence
Requires-Python: >=3.6.0
Requires-Dist: numpy
Requires-Dist: pandas
Requires-Dist: tqdm
Requires-Dist: click
Requires-Dist: requests
Requires-Dist: ipython
